Metadata-Version: 2.1
Name: ai-incantations
Version: 0.0.1
Summary: A library to manage and develop prompts
Author: Supreeth Rao
License-File: LICENSE
